CriCodecsEx.cpython-312-darwin.so
pycricodecsex-0.0.5.dist-info/RECORD
pycricodecsex-0.0.5.dist-info/WHEEL
pycricodecsex-0.0.5.dist-info/top_level.txt
pycricodecsex-0.0.5.dist-info/METADATA
pycricodecsex-0.0.5.dist-info/licenses/LICENSE
PyCriCodecsEx/adx.py
PyCriCodecsEx/__init__.py
PyCriCodecsEx/chunk.py
PyCriCodecsEx/hca.py
PyCriCodecsEx/cpk.py
PyCriCodecsEx/usm.py
PyCriCodecsEx/acb.py
PyCriCodecsEx/awb.py
PyCriCodecsEx/utf.py
