Metadata-Version: 2.4
Name: PyCriCodecsEx
Version: 0.0.5
Summary: Criware formats library for Python
Home-page: https://mos9527.github.io/PyCriCodecsEx/
Classifier: Programming Language :: Python :: 3
Classifier: License :: OSI Approved :: MIT License
Classifier: Operating System :: OS Independent
Requires-Python: >=3.10
License-File: LICENSE
Provides-Extra: usm
Requires-Dist: ffmpeg-python; extra == "usm"
Dynamic: classifier
Dynamic: description
Dynamic: description-content-type
Dynamic: home-page
Dynamic: license-file
Dynamic: provides-extra
Dynamic: requires-python
Dynamic: summary
